scratchmls/__init__.py
scratchmls/metrics/__init__.py
scratchmls/metrics/_accuracy.py
scratchmls/metrics/_r2_score.py
scratchmls/metrics/_rse.py
scratchmls/models/__init__.py
scratchmls/models/_knn.py
scratchmls/models/_linearreg.py
scratchmls/models/_logistic.py
tests/__init__.py
tests/test_knn.py
tests/test_linear.py
tests/test_logistic.py
tests/test_r2.py
scratchmls-0.0.3.dist-info/LICENSE
scratchmls-0.0.3.dist-info/METADATA
scratchmls-0.0.3.dist-info/WHEEL
scratchmls-0.0.3.dist-info/top_level.txt
scratchmls-0.0.3.dist-info/RECORD
