Metadata-Version: 2.1
Name: scratchmls
Version: 0.0.3
Summary: Custom Python library for Machine Learning
Home-page: UNKNOWN
Author: Faraz Khan
Author-email: farazkhan138@gmail.com
License: MIT
Keywords: MachineLearning
Platform: UNKNOWN
Classifier: Development Status :: 5 - Production/Stable
Classifier: Intended Audience :: Education
Classifier: Operating System :: Microsoft :: Windows :: Windows 10
Classifier: License :: OSI Approved :: MIT License
Classifier: Programming Language :: Python :: 3
Requires-Dist: numpy
